simparx/__init__.py
simparx/exception.py
simparx/simpar.py
simparx-0.2.0.dist-info/LICENSE
simparx-0.2.0.dist-info/METADATA
simparx-0.2.0.dist-info/WHEEL
simparx-0.2.0.dist-info/RECORD
